mpsf/__init__.py
mpsf/mpsf.py
mpsf-0.3.1.dist-info/LICENSE
mpsf-0.3.1.dist-info/WHEEL
mpsf-0.3.1.dist-info/METADATA
mpsf-0.3.1.dist-info/RECORD
